{"max":10,"id":"169","sid":"0","url":"","page":"1","debug":false,"cache":false,"res":[{"title":"(C93)[Flameworks(\u306a\u30fc\u3055\u3093)] forget","url":"http:\/\/www.jueduifucong.com\/6501.html","cover":"http:\/\/www.jueduifucong.com\/wp-content\/uploads\/thumbnail\/6501_0100_200.jpg"},{"title":"(C92)[mysuite] SUITE FANTASY 3","url":"http:\/\/www.jueduifucong.com\/6487.html","cover":"http:\/\/www.jueduifucong.com\/wp-content\/uploads\/thumbnail\/6487_309_Vira_summer138_200.jpg"},{"title":"Suite Blue","url":"http:\/\/www.jueduifucong.com\/6464.html","cover":"http:\/\/www.jueduifucong.com\/wp-content\/uploads\/thumbnail\/6464_191_humihumi2_142_200.jpg"},{"title":"\u6781\u54c1Cosplay\u5973\u738b\u96ea\u9732\u513f\u65e0\u5723\u5149\u5957\u56fe","url":"http:\/\/www.jueduifucong.com\/6379.html","cover":"http:\/\/www.jueduifucong.com\/wp-content\/uploads\/thumbnail\/6379_C_44_200.jpg"},{"title":"\u5984\u60f3\u53cc\u5b50\u62c9\u59c6\u857e\u59c6\u767e\u5408\u59d0\u59b9\u82b1cosplay\u5199\u771f\u5957\u56fe","url":"http:\/\/www.jueduifucong.com\/6224.html","cover":"http:\/\/www.jueduifucong.com\/wp-content\/uploads\/thumbnail\/6224_mousouhutago0165_200.jpg"},{"title":"\u4e60\u5446\u5446\u6027\u611fcosplay\u5199\u771f\u5957\u56fe\u7eef\u8272\u5929\u4f7f","url":"http:\/\/www.jueduifucong.com\/6128.html","cover":"http:\/\/www.jueduifucong.com\/wp-content\/uploads\/thumbnail\/6128_xidai2_200.jpg"},{"title":"\u3010\u5c11\u5973\u6620\u756b\u3011\u7f8e\u4e91\u00b7\u91d1\u52aa\u6885\u5c14cosplay\u5199\u771f\u5957\u56fe","url":"http:\/\/www.jueduifucong.com\/6040.html","cover":"http:\/\/www.jueduifucong.com\/wp-content\/uploads\/thumbnail\/6040_63_ff_63_200.jpg"},{"title":"\u3010\u5c11\u5973\u6620\u756b\u3011\u79bb\u5c9b\u6816\u59ec\u9ed1\u4e1d\u817f\u63a7\u8db3\u63a7\u798f\u5229cosplay\u5199\u771f\u5957\u56fe","url":"http:\/\/www.jueduifucong.com\/6028.html","cover":"http:\/\/www.jueduifucong.com\/wp-content\/uploads\/thumbnail\/6028_SH015_200.jpg"},{"title":"\u5996\u7cbe\u6620\u753b\u53f8\u673a\u661flw\u65f6\u5d0e\u72c2\u4e09\u9ed1\u4e1d\u817f\u63a7\u798f\u5229cosplay\u5199\u771f\u5957\u56fe","url":"http:\/\/www.jueduifucong.com\/5978.html","cover":"http:\/\/www.jueduifucong.com\/wp-content\/uploads\/thumbnail\/5978_sijixing2_200.jpg"},{"title":"\u3010\u5c11\u5973\u6620\u756b\u3011cosplay\u9038\u4ed9\u5199\u771f\u5957\u56fe","url":"http:\/\/www.jueduifucong.com\/5915.html","cover":"http:\/\/www.jueduifucong.com\/wp-content\/uploads\/thumbnail\/5915_26_IMG_4867_200.jpg"},{"title":"[Mikehouse] \u9e7f\u5cf6\u56db\u5a18cosplay\u5199\u771f\u5957\u56fe","url":"http:\/\/www.jueduifucong.com\/5903.html","cover":"http:\/\/www.jueduifucong.com\/wp-content\/uploads\/thumbnail\/5903_A013_200.jpg"},{"title":"\u4e8c\u6b21\u5143\u7f8e\u5973\u5973\u4ec6\u857e\u59c6cosplay\u798f\u5229\u5199\u771f\u56fe\u7247","url":"http:\/\/www.jueduifucong.com\/5826.html","cover":"http:\/\/www.jueduifucong.com\/wp-content\/uploads\/thumbnail\/5826_20170828050159624_200.jpg"}]}